jsondatasave/__init__.py
jsondatasave-1.6.1.dist-info/METADATA
jsondatasave-1.6.1.dist-info/WHEEL
jsondatasave-1.6.1.dist-info/top_level.txt
jsondatasave-1.6.1.dist-info/RECORD
