Metadata-Version: 2.1
Name: jsondatasave
Version: 1.6.1
Summary: Facilitating the process to store JSON data
Home-page: https://github.com/SimplyYourAverageDev/jsondatasave
Author: YourAverageDev
License: MIT
Project-URL: Bug Tracker, https://github.com/SimplyYourAverageDev/jsondatasave/issues
Project-URL: Documentation, https://github.com/SimplyYourAverageDev/jsondatasave#readme
Keywords: python,JSON,Data Storage
Classifier: Development Status :: 5 - Production/Stable
Classifier: Intended Audience :: Developers
Classifier: License :: OSI Approved :: MIT License
Classifier: Operating System :: Unix
Classifier: Operating System :: MacOS :: MacOS X
Classifier: Operating System :: Microsoft :: Windows
Classifier: Programming Language :: Python :: 3
Classifier: Programming Language :: Python :: 3.7
Classifier: Programming Language :: Python :: 3.8
Classifier: Programming Language :: Python :: 3.9
Classifier: Programming Language :: Python :: 3.10
Classifier: Programming Language :: Python :: 3.11
Classifier: Topic :: Software Development :: Libraries :: Python Modules
